metadata_driver_mongodb/__init__.py
metadata_driver_mongodb/indexes.py
metadata_driver_mongodb/instance.py
metadata_driver_mongodb/plugin.py
metadata_driver_mongodb/utils.py
nevermined_metadata_driver_mongodb-0.1.0.dist-info/LICENSE
nevermined_metadata_driver_mongodb-0.1.0.dist-info/METADATA
nevermined_metadata_driver_mongodb-0.1.0.dist-info/NOTICE
nevermined_metadata_driver_mongodb-0.1.0.dist-info/WHEEL
nevermined_metadata_driver_mongodb-0.1.0.dist-info/top_level.txt
nevermined_metadata_driver_mongodb-0.1.0.dist-info/RECORD
