Metadata-Version: 2.1
Name: nevermined-metadata-driver-mongodb
Version: 0.1.0
Summary: 🐳 Mongo DB driver (Python).
Home-page: https://github.com/nevermined-io/metadata-driver-mongodb
Author: nevermined-io
Author-email: root@nevermined.io
License: Apache Software License 2.0
Keywords: nevermined-metadata-driver-mongodb
Platform: UNKNOWN
Classifier: Development Status :: 2 - Pre-Alpha
Classifier: Intended Audience :: Developers
Classifier: License :: OSI Approved :: Apache Software License
Classifier: Natural Language :: English
Classifier: Programming Language :: Python :: 3.4
Classifier: Programming Language :: Python :: 3.5
Classifier: Programming Language :: Python :: 3.6
Requires-Dist: nevermined-metadata-driver-interface
Requires-Dist: pymongo
